adjustpy-0.1.1.dist-info/METADATA
adjustpy-0.1.1.dist-info/WHEEL
adjustpy-0.1.1.dist-info/license_files/LICENSE
adjustpy/__init__.py
adjustpy/adjustpy.cpython-311-x86_64-linux-gnu.so
adjustpy-0.1.1.dist-info/RECORD
