Metadata-Version: 2.1
Name: adjustpy
Version: 0.1.1
Classifier: Programming Language :: Rust
Classifier: Programming Language :: Python :: Implementation :: CPython
Classifier: Programming Language :: Python :: Implementation :: PyPy
Classifier: License :: OSI Approved :: MIT License
Requires-Dist: numpy >=1.17.0
License-File: LICENSE
Author-email: Noam Teyssier <noam.teyssier@ucsf.edu>
Requires-Python: >=3.7
Project-URL: Source, https://github.com/noamteyssier/adjustpy
